tle_tracker/__init__.py
tle_tracker/__main__.py
tle_tracker/data.py
tle_tracker/mqtt_interface.py
tle_tracker/tle_file_handler.py
tle_tracker-0.3.0.dist-info/METADATA
tle_tracker-0.3.0.dist-info/WHEEL
tle_tracker-0.3.0.dist-info/RECORD
