Metadata-Version: 2.3
Name: TLE-tracker
Version: 0.3.0
Summary: 
Author: dawid.robak
Author-email: dawid.robak1704@gmail.com
Requires-Python: >=3.12,<4.0
Classifier: Programming Language :: Python :: 3
Classifier: Programming Language :: Python :: 3.12
Classifier: Programming Language :: Python :: 3.13
Requires-Dist: paho-mqtt (>=2.1.0,<3.0.0)
Requires-Dist: pydantic (>=2.11.5,<3.0.0)
Requires-Dist: skyfield (>=1.53,<2.0)
Requires-Dist: uvicorn (>=0.34.2,<0.35.0)
Requires-Dist: watchdog (>=6.0.0,<7.0.0)
